.project
.pydevproject
MANIFEST.in
README.txt
setup.py
docs/HISTORY.txt
docs/mobile_theming.txt
gomobiletheme/__init__.py
gomobiletheme.basic.egg-info/PKG-INFO
gomobiletheme.basic.egg-info/SOURCES.txt
gomobiletheme.basic.egg-info/dependency_links.txt
gomobiletheme.basic.egg-info/entry_points.txt
gomobiletheme.basic.egg-info/namespace_packages.txt
gomobiletheme.basic.egg-info/not-zip-safe
gomobiletheme.basic.egg-info/requires.txt
gomobiletheme.basic.egg-info/top_level.txt
gomobiletheme/basic/__init__.py
gomobiletheme/basic/configure.zcml
gomobiletheme/basic/content.zcml
gomobiletheme/basic/i18n.sh
gomobiletheme/basic/interfaces.py
gomobiletheme/basic/setuphandlers.py
gomobiletheme/basic/tests.py
gomobiletheme/basic/viewlets.py
gomobiletheme/basic/views.py
gomobiletheme/basic/i18n/gomobiletheme.basic-plone-en.po
gomobiletheme/basic/i18n/gomobiletheme.basic-plone-es.po
gomobiletheme/basic/i18n/gomobiletheme.basic-plone-fi.po
gomobiletheme/basic/i18n/gomobiletheme.basic-plone.pot
gomobiletheme/basic/locales/ manual.pot
gomobiletheme/basic/locales/gomobiletheme.basic.pot
gomobiletheme/basic/locales/en/LC_MESSAGES/gomobiletheme.basic.po
gomobiletheme/basic/locales/es/LC_MESSAGES/gomobiletheme.basic.po
gomobiletheme/basic/locales/fi/LC_MESSAGES/gomobiletheme.basic.po
gomobiletheme/basic/profiles/default/gomobiletheme.basic.marker.txt
gomobiletheme/basic/profiles/default/metadata.xml
gomobiletheme/basic/profiles/default/propertiestool.xml
gomobiletheme/basic/profiles/default/skins.xml
gomobiletheme/basic/profiles/plone3/README.txt
gomobiletheme/basic/profiles/plone3/skins.xml
gomobiletheme/basic/skins/gomobiletheme_basic/batch_macros.pt
gomobiletheme/basic/skins/gomobiletheme_basic/document_view.pt
gomobiletheme/basic/skins/gomobiletheme_basic/document_view.pt.metadata
gomobiletheme/basic/skins/gomobiletheme_basic/event_view.pt
gomobiletheme/basic/skins/gomobiletheme_basic/event_view.pt.metadata
gomobiletheme/basic/skins/gomobiletheme_basic/folder_listing.pt
gomobiletheme/basic/skins/gomobiletheme_basic/folder_listing.pt.metadata
gomobiletheme/basic/skins/gomobiletheme_basic/folder_summary_view.pt
gomobiletheme/basic/skins/gomobiletheme_basic/folder_summary_view.pt.metadata
gomobiletheme/basic/skins/gomobiletheme_basic/main_template.pt
gomobiletheme/basic/skins/gomobiletheme_basic/search.pt
