Metadata-Version: 1.1
Name: gomobiletheme.basic
Version: 1.0.10
Summary: Default mobile theme for mFabrik Web and Mobile sites
Home-page: http://webandmobile.mfabrik.com
Author: mFabrik Research Oy
Author-email: research@mfabrik.com
License: GPL
Platform: UNKNOWN
Classifier: Programming Language :: Python
Classifier: Topic :: Software Development :: Libraries :: Python Modules
